slideslurp
