Metadata-Version: 1.1
Name: slideslurp
Version: 0.0.3
Summary: SlideShare to PDF
Home-page: https://github.com/hellerve/slideslurp
Author: Veit Heller
Author-email: veit@veitheller.de
License: MIT License
Download-URL: https://github.com/hellerve/slideslurp/tarball/0.0.3
Platform: UNKNOWN
